hdltypes/__init__.py
hdltypes/array.py
hdltypes/logic.py
hdltypes/logic_array.py
hdltypes/py.typed
hdltypes/range.py
hdltypes/types.py
hdltypes/version.py
hdltypes-0.2.1.dist-info/LICENSE
hdltypes-0.2.1.dist-info/METADATA
hdltypes-0.2.1.dist-info/WHEEL
hdltypes-0.2.1.dist-info/top_level.txt
hdltypes-0.2.1.dist-info/RECORD
