Metadata-Version: 2.1
Name: hdltypes
Version: 0.2.1
Summary: Models of VHDL datatypes in Python
Home-page: https://github.com/ktbarrett/pyhdltypes
Author: Kaleb Barrett
Author-email: dev.ktbarrett@gmail.com
License: MIT
Platform: UNKNOWN
Classifier: Development Status :: 2 - Pre-Alpha
Classifier: Intended Audience :: Developers
Classifier: License :: OSI Approved :: MIT License
Classifier: Programming Language :: Python :: 3
Requires-Python: >=3.8, <4
License-File: LICENSE
